odoo/addons/shopfloor_purchase_base/README.rst
odoo/addons/shopfloor_purchase_base/__init__.py
odoo/addons/shopfloor_purchase_base/__manifest__.py
odoo/addons/shopfloor_purchase_base/actions/__init__.py
odoo/addons/shopfloor_purchase_base/actions/data.py
odoo/addons/shopfloor_purchase_base/actions/schema.py
odoo/addons/shopfloor_purchase_base/i18n/shopfloor_purchase_base.pot
odoo/addons/shopfloor_purchase_base/readme/CONTRIBUTORS.rst
odoo/addons/shopfloor_purchase_base/readme/DESCRIPTION.rst
odoo/addons/shopfloor_purchase_base/static/description/icon.png
odoo/addons/shopfloor_purchase_base/static/description/index.html
odoo/addons/shopfloor_purchase_base/tests/__init__.py
odoo/addons/shopfloor_purchase_base/tests/test_actions_data.py
odoo14_addon_shopfloor_purchase_base-14.0.1.1.0.dist-info/METADATA
odoo14_addon_shopfloor_purchase_base-14.0.1.1.0.dist-info/WHEEL
odoo14_addon_shopfloor_purchase_base-14.0.1.1.0.dist-info/top_level.txt
odoo14_addon_shopfloor_purchase_base-14.0.1.1.0.dist-info/RECORD
